README.txt
fcool.py
setup.py
fcool.egg-info/PKG-INFO
fcool.egg-info/SOURCES.txt
fcool.egg-info/dependency_links.txt
fcool.egg-info/top_level.txt
fcool.egg-info/zip-safe