Metadata-Version: 1.1
Name: fcool
Version: 0.1.3
Summary: A cool tool for functional programming. Funtions can be operated directly with definition domain that can be used in type testing
Home-page: https://github.com/Freakwill/fcool
Author: William Song
Author-email: songcwzjut@163.com
License: MIT
Keywords: Functional Programming,Type Testing
Platform: UNKNOWN
Classifier: License :: Public Domain
Classifier: Programming Language :: Python
Classifier: Programming Language :: Python :: 3.6
Classifier: Intended Audience :: Science/Research
Classifier: Operating System :: OS Independent
Classifier: Topic :: Scientific/Engineering :: Mathematics
Classifier: Natural Language :: English
